Metadata-Version: 2.1
Name: pycel-fixed
Version: 1.0b27
Summary: A library for compiling excel spreadsheets to python code & visualizing them as a graph
Home-page: https://github.com/stephenrauch/pycel
Author: Dirk Gorissen, Stephen Rauch
Author-email: dgorissen@gmail.com
Maintainer: Stephen Rauch
Maintainer-email: stephen.rauch+pycel@gmail.com
License: UNKNOWN
Keywords: excel compiler formula parser
Platform: UNKNOWN
Classifier: Development Status :: 4 - Beta
Classifier: Intended Audience :: Developers
Classifier: License :: OSI Approved :: GNU General Public License v3 (GPLv3)
Classifier: Operating System :: OS Independent
Classifier: Programming Language :: Python
Classifier: Programming Language :: Python :: 3
Classifier: Programming Language :: Python :: 3.6
Classifier: Programming Language :: Python :: 3.7
Classifier: Programming Language :: Python :: 3.8
Classifier: Programming Language :: Python :: 3.9
Classifier: Topic :: Software Development :: Libraries :: Python Modules
Requires-Python: >=3.5
Requires-Dist: networkx (<2.6,>=2.0)
Requires-Dist: numpy
Requires-Dist: openpyxl (>=2.6.2)
Requires-Dist: python-dateutil
Requires-Dist: ruamel.yaml
